{"cameraMode":{"drawMode":0,"name":"Shaded","section":"Shading Mode"},"sceneLighting":true,"audioPlay":false,"sceneViewState":{"showFog":true,"showMaterialUpdate":false,"showSkybox":true,"showFlares":true,"showImageEffects":true,"showParticleSystems":true},"in2DMode":false,"pivot":{"x":96.77228546142578,"y":57.90900421142578,"z":15.4583740234375},"rotation":{"x":0.04063209891319275,"y":-0.8868784308433533,"z":0.45329681038856509,"w":0.07949727028608322},"size":8.167728424072266,"orthographic":false}